{"name":"Menu Proceso/Opcion Ingreso Proceso","id":"lex--\u003e-desacoplamiento;menu-proceso/opcion-ingreso-proceso","testSteps":[{"number":1,"description":"Example #1: {tipo_doc_do\u003dCC, num_doc_do\u003d123, tipo_doc_te\u003dCC, num_doc_te\u003d456, tipo_doc_apo\u003dCC, num_doc_apo\u003d789}","duration":14882,"startTime":"2020-08-26T09:17:45.008-05:00[America/Bogota]","screenshots":[{"screenshot":"49c6f7292a7260455dac0acc5dd5904e9eb6618d1cdbba52731a3ea06a9f2e65.png","timeStamp":1598451479890}],"result":"SUCCESS","precondition":false,"level":0,"children":[{"number":2,"description":"Given que un administrador quiere ingresar a Lex","duration":4291,"startTime":"2020-08-26T09:17:45.008-05:00[America/Bogota]","screenshots":[{"screenshot":"c5495955f4d085bb230633bf6de683870e1996f5b3ca179aaa35d72f2a144da1.png","timeStamp":1598451469299}],"result":"SUCCESS","precondition":false,"level":1},{"number":3,"description":"When el ingresa datos usuario \"apossor\" y clave \"12345\"","duration":866,"startTime":"2020-08-26T09:17:49.301-05:00[America/Bogota]","screenshots":[{"screenshot":"7dc1e7fa41acda4acac9e6418275351f5bb9ab03eefd1cf7dd589484fba47236.png","timeStamp":1598451470167}],"result":"SUCCESS","precondition":false,"level":1},{"number":4,"description":"Then ve la pagina principal de Lex","duration":350,"startTime":"2020-08-26T09:17:50.167-05:00[America/Bogota]","screenshots":[{"screenshot":"7dc1e7fa41acda4acac9e6418275351f5bb9ab03eefd1cf7dd589484fba47236.png","timeStamp":1598451470517}],"result":"SUCCESS","precondition":false,"level":1},{"number":5,"description":"Given que un administrador ingresa a la opcion ingreso proceso","duration":1122,"startTime":"2020-08-26T09:17:50.517-05:00[America/Bogota]","screenshots":[{"screenshot":"4e9ba6b9fdb3e643ae062feb1b9d3290244dbb42450505774e216780088e11d6.png","timeStamp":1598451471639}],"result":"SUCCESS","precondition":false,"level":1},{"number":6,"description":"When el selecciona el area de competencia","duration":663,"startTime":"2020-08-26T09:17:51.639-05:00[America/Bogota]","screenshots":[{"screenshot":"f578047b98dff2bea11c6880abfb2684cef20daca38dc466a321eb5136730d15.png","timeStamp":1598451472302}],"result":"SUCCESS","precondition":false,"level":1},{"number":7,"description":"And ingresa los datos del Demandado \"CC\" y \"123\"","duration":821,"startTime":"2020-08-26T09:17:52.303-05:00[America/Bogota]","screenshots":[{"screenshot":"a59a64f34159954e5bddb42e78b4ee61467409c26c2aa38286fea0e75cf22bef.png","timeStamp":1598451473124}],"result":"SUCCESS","precondition":false,"level":1},{"number":8,"description":"And ingresa los datos del Demandante \"CC\" y \"456\"","duration":771,"startTime":"2020-08-26T09:17:53.125-05:00[America/Bogota]","screenshots":[{"screenshot":"c21ce3dcd9ce9ac002e471abd85cb641e27cce704751a2b07f18ef1b22e58e16.png","timeStamp":1598451473896}],"result":"SUCCESS","precondition":false,"level":1},{"number":9,"description":"And ingresa los datos del Apoderado Contraparte \"CC\" y \"789\"","duration":788,"startTime":"2020-08-26T09:17:53.896-05:00[America/Bogota]","screenshots":[{"screenshot":"51f7bf05ff3e522ef7777577a2054741684e747e77ceaf73262b8012011a7de0.png","timeStamp":1598451474684}],"result":"SUCCESS","precondition":false,"level":1},{"number":10,"description":"And ingresa los datos del Consultorio Juridico","duration":2871,"startTime":"2020-08-26T09:17:54.684-05:00[America/Bogota]","screenshots":[{"screenshot":"e63af51542c23f7823e5a022ca11b4d600f8b8da00b919431824dd298a34760b.png","timeStamp":1598451477555}],"result":"SUCCESS","precondition":false,"level":1},{"number":11,"description":"Then el ve en pantalla el mensaje de exito del proceso ingresado","duration":2334,"startTime":"2020-08-26T09:17:57.555-05:00[America/Bogota]","screenshots":[{"screenshot":"49c6f7292a7260455dac0acc5dd5904e9eb6618d1cdbba52731a3ea06a9f2e65.png","timeStamp":1598451479889}],"result":"SUCCESS","precondition":false,"level":1}]},{"number":12,"description":"Example #2: {tipo_doc_do\u003dCE, num_doc_do\u003d22222222223333333333, tipo_doc_te\u003dPP, num_doc_te\u003d22222222223333333333, tipo_doc_apo\u003dRE, num_doc_apo\u003d22227777777777777777}","duration":23677,"startTime":"2020-08-26T09:17:59.972-05:00[America/Bogota]","screenshots":[{"screenshot":"a08ac9c499fa9b946e7e7fddb4a6d8873f4a59d7d3495769f22c62ae3ac597d1.png","timeStamp":1598451503649}],"result":"SUCCESS","precondition":false,"level":0,"children":[{"number":13,"description":"Given que un administrador quiere ingresar a Lex","duration":3038,"startTime":"2020-08-26T09:17:59.972-05:00[America/Bogota]","screenshots":[{"screenshot":"d320f3238c2d190086d101212cacf810c5922d9ccd3d046852f1782678afd31c.png","timeStamp":1598451483010}],"result":"SUCCESS","precondition":false,"level":1},{"number":14,"description":"When el ingresa datos usuario \"apossor\" y clave \"12345\"","duration":811,"startTime":"2020-08-26T09:18:03.010-05:00[America/Bogota]","screenshots":[{"screenshot":"7dc1e7fa41acda4acac9e6418275351f5bb9ab03eefd1cf7dd589484fba47236.png","timeStamp":1598451483821}],"result":"SUCCESS","precondition":false,"level":1},{"number":15,"description":"Then ve la pagina principal de Lex","duration":311,"startTime":"2020-08-26T09:18:03.822-05:00[America/Bogota]","screenshots":[{"screenshot":"7dc1e7fa41acda4acac9e6418275351f5bb9ab03eefd1cf7dd589484fba47236.png","timeStamp":1598451484133}],"result":"SUCCESS","precondition":false,"level":1},{"number":16,"description":"Given que un administrador ingresa a la opcion ingreso proceso","duration":1073,"startTime":"2020-08-26T09:18:04.133-05:00[America/Bogota]","screenshots":[{"screenshot":"4e9ba6b9fdb3e643ae062feb1b9d3290244dbb42450505774e216780088e11d6.png","timeStamp":1598451485206}],"result":"SUCCESS","precondition":false,"level":1},{"number":17,"description":"When el selecciona el area de competencia","duration":541,"startTime":"2020-08-26T09:18:05.206-05:00[America/Bogota]","screenshots":[{"screenshot":"f578047b98dff2bea11c6880abfb2684cef20daca38dc466a321eb5136730d15.png","timeStamp":1598451485747}],"result":"SUCCESS","precondition":false,"level":1},{"number":18,"description":"And ingresa los datos del Demandado \"CE\" y \"22222222223333333333\"","duration":838,"startTime":"2020-08-26T09:18:05.747-05:00[America/Bogota]","screenshots":[{"screenshot":"57bb8a63869947d94ed6ee38ec8dcfd64e8eec3a1afadbf94fc07b3a1ac15a85.png","timeStamp":1598451486585}],"result":"SUCCESS","precondition":false,"level":1},{"number":19,"description":"And ingresa los datos del Demandante \"PP\" y \"22222222223333333333\"","duration":924,"startTime":"2020-08-26T09:18:06.585-05:00[America/Bogota]","screenshots":[{"screenshot":"8ad39488f5b81c2ad4bbe7a3fd7db5fb65d7ab875f09bcf0064f30950f0bb6ad.png","timeStamp":1598451487509}],"result":"SUCCESS","precondition":false,"level":1},{"number":20,"description":"And ingresa los datos del Apoderado Contraparte \"RE\" y \"22227777777777777777\"","duration":981,"startTime":"2020-08-26T09:18:07.509-05:00[America/Bogota]","screenshots":[{"screenshot":"500fa1a63014fb4ed39ecf632680c27502f88b2216bb6a74cc0dd482a3bd3f09.png","timeStamp":1598451488490}],"result":"SUCCESS","precondition":false,"level":1},{"number":21,"description":"And ingresa los datos del Consultorio Juridico","duration":2711,"startTime":"2020-08-26T09:18:08.490-05:00[America/Bogota]","screenshots":[{"screenshot":"4db1d6854f5d141962cae05b8e74194ec69fafc4ed703a45059fa9de137ca0e3.png","timeStamp":1598451491201}],"result":"SUCCESS","precondition":false,"level":1},{"number":22,"description":"Then el ve en pantalla el mensaje de exito del proceso ingresado","duration":12445,"startTime":"2020-08-26T09:18:11.201-05:00[America/Bogota]","screenshots":[{"screenshot":"a08ac9c499fa9b946e7e7fddb4a6d8873f4a59d7d3495769f22c62ae3ac597d1.png","timeStamp":1598451503646}],"result":"SUCCESS","precondition":false,"level":1}]}],"userStory":{"id":"lex--\u003e-desacoplamiento","storyName":"LEX -\u003e Desacoplamiento","path":"src/test/resources/features/Lex.feature","narrative":"  Como analista DINFO\n  Quiero verificar que todas las funcionalidades de Lex esten disponibles despues del desacoplamiento\n  para garantizar que funcionan con el modelo canonico","type":"feature"},"featureTag":{"name":"Features/LEX -\u003e Desacoplamiento","type":"feature"},"title":"Menu Proceso/Opcion Ingreso Proceso","backgroundTitle":"Login a la aplicacion Lex","backgroundDescription":"","tags":[{"name":"LEX -\u003e Desacoplamiento","type":"feature"}],"startTime":"2020-08-26T09:17:45.004-05:00[America/Bogota]","duration":38646,"projectKey":"","sessionId":"ca9e52466ce6db4be35752b1391441d6","driver":"chrome","dataTable":{"headers":["tipo_doc_do","num_doc_do","tipo_doc_te","num_doc_te","tipo_doc_apo","num_doc_apo"],"rows":[{"values":["CC","123","CC","456","CC","789"],"result":"SUCCESS"},{"values":["CE","22222222223333333333","PP","22222222223333333333","RE","22227777777777777777"],"result":"SUCCESS"}],"predefinedRows":true,"scenarioOutline":"Given que un administrador ingresa a la opcion ingreso proceso\n\rWhen el selecciona el area de competencia\n\rAnd ingresa los datos del Demandado \"\u003ctipo_doc_do\u003e\" y \"\u003cnum_doc_do\u003e\"\n\rAnd ingresa los datos del Demandante \"\u003ctipo_doc_te\u003e\" y \"\u003cnum_doc_te\u003e\"\n\rAnd ingresa los datos del Apoderado Contraparte \"\u003ctipo_doc_apo\u003e\" y \"\u003cnum_doc_apo\u003e\"\n\rAnd ingresa los datos del Consultorio Juridico\n\rThen el ve en pantalla el mensaje de exito del proceso ingresado\n\r","dataSetDescriptors":[{"startRow":0,"rowCount":0,"name":""}]},"manual":false,"testSource":"Cucumber","result":"SUCCESS","scenarioOutline":"Given que un administrador ingresa a la opcion ingreso proceso\r\nWhen el selecciona el area de competencia\r\nAnd ingresa los datos del Demandado \"\u003ctipo_doc_do\u003e\" y \"\u003cnum_doc_do\u003e\"\r\nAnd ingresa los datos del Demandante \"\u003ctipo_doc_te\u003e\" y \"\u003cnum_doc_te\u003e\"\r\nAnd ingresa los datos del Apoderado Contraparte \"\u003ctipo_doc_apo\u003e\" y \"\u003cnum_doc_apo\u003e\"\r\nAnd ingresa los datos del Consultorio Juridico\r\nThen el ve en pantalla el mensaje de exito del proceso ingresado"}